[
  { "id": 901, "vietnamese": "Đồng ý cả hai tay hai chân / Chuẩn cơm mẹ nấu" },
  { "id": 902, "vietnamese": "Não cá vàng quá / Nhớ trước quên sau" },
  { "id": 903, "vietnamese": "Quán mời nhé / Miễn phí nha" },
  { "id": 904, "vietnamese": "Nên hỏi thêm ý kiến người khác xem / Khám chỗ khác xem sao" },
  { "id": 905, "vietnamese": "Cậu là số một / Không ai sánh bằng cậu" },
  { "id": 906, "vietnamese": "Đừng có chém gió / Đừng lừa tôi" },
  { "id": 907, "vietnamese": "Đang phân vân quá / Khó nghĩ quá" },
  { "id": 908, "vietnamese": "Cậu bị ngáo à? / Mất trí rồi à?" },
  { "id": 909, "vietnamese": "Biết thế thôi nhé / Sống để bụng chết mang theo nhé" },
  { "id": 910, "vietnamese": "Biết quy trình rồi chứ? / Cứ theo nếp cũ mà làm" },
  { "id": 911, "vietnamese": "Lên voi xuống chó / Cuộc đời thăng trầm" },
  { "id": 912, "vietnamese": "Ngưỡng mộ cậu lắm / Thần tượng cậu đấy" },
  { "id": 913, "vietnamese": "Được tâng bốc quá đà thôi / Chẳng thần thánh thế đâu" },
  { "id": 914, "vietnamese": "Nói tóm lại là / Túm cái váy lại là" },
  { "id": 915, "vietnamese": "Tôi không để bụng đâu / Tôi không thù dai đâu" },
  { "id": 916, "vietnamese": "Không nhớ ngay được / Tự dưng quên mất" },
  { "id": 917, "vietnamese": "Ngán tận cổ rồi / Chán ngấy rồi" },
  { "id": 918, "vietnamese": "Việc ngập đầu rồi / Bận tối mắt tối mũi" },
  { "id": 919, "vietnamese": "Tôi mù đường / Không biết đường sá gì đâu" },
  { "id": 920, "vietnamese": "Vẫn ổn chứ? / Cố gắng nhé" },
  { "id": 921, "vietnamese": "Cứ làm tới đi / Làm thôi, đừng nghĩ nhiều" },
  { "id": 922, "vietnamese": "Cậu đang tính gì thế? / Có cao kiến gì không?" },
  { "id": 923, "vietnamese": "Đừng như thế mà / Sao lại thái độ thế" },
  { "id": 924, "vietnamese": "Bắt đầu thôi / Khai máy thôi" },
  { "id": 925, "vietnamese": "Đắt lòi kèn / Đắt cắt cổ" },
  { "id": 926, "vietnamese": "Làm cho có tâm chút đi / Đừng làm kiểu đối phó" },
  { "id": 927, "vietnamese": "Đang định nói thế / Cậu nói hộ lòng tôi rồi" },
  { "id": 928, "vietnamese": "Quá đáng rồi đấy / Vượt giới hạn rồi" },
  { "id": 929, "vietnamese": "Ổng pro lắm / Lão này có nghề đấy" },
  { "id": 930, "vietnamese": "Cố lên! / Gắng tí nữa thôi!" },
  { "id": 931, "vietnamese": "Bỏ thói quen đó đi / Cai đi" },
  { "id": 932, "vietnamese": "Chuẩn không cần chỉnh / Phán chuẩn đấy" },
  { "id": 933, "vietnamese": "Đầu óc dạo này chán quá / Não bộ xuống cấp rồi" },
  { "id": 934, "vietnamese": "Bị chém đẹp rồi / Mua hớ rồi" },
  { "id": 935, "vietnamese": "Đang lượn lờ ngoài đường / Đang đi công chuyện" },
  { "id": 936, "vietnamese": "Cứ ám ảnh mãi / Không gạt ra khỏi đầu được" },
  { "id": 937, "vietnamese": "Bớt ảo tưởng đi / Đừng tự lừa mình nữa" },
  { "id": 938, "vietnamese": "Không dễ ăn đâu / Chua lắm đấy" },
  { "id": 939, "vietnamese": "Cho qua đi / Bỏ đi mà làm người" },
  { "id": 940, "vietnamese": "Tỉnh lại đi / Khôn ra đi" },
  { "id": 941, "vietnamese": "Nghỉ thôi / Hôm nay tới đây thôi" },
  { "id": 942, "vietnamese": "Lớn rồi thì cư xử cho đúng tuổi đi / Đừng trẻ trâu nữa" },
  { "id": 943, "vietnamese": "Chả hiểu mô tê gì / Nghe như vịt nghe sấm" },
  { "id": 944, "vietnamese": "Nay có mở hàng không? / Hôm nay quán có bán không?" },
  { "id": 945, "vietnamese": "Đừng chuyện bé xé ra to / Có gì đâu mà rùm beng lên" },
  { "id": 946, "vietnamese": "Tóm lại là / Ngắn gọn là" },
  { "id": 947, "vietnamese": "Cấm bép xép nhé / Giữ mồm giữ miệng nhé" },
  { "id": 948, "vietnamese": "Quán mở chưa ạ? / Còn bán không ạ?" },
  { "id": 949, "vietnamese": "Tôi sẽ canh chừng kỹ / Mở to mắt ra mà tìm" },
  { "id": 950, "vietnamese": "Luôn ủng hộ cậu / Có tôi bảo kê" },
  { "id": 951, "vietnamese": "Lại thế nữa rồi / Lại bài cũ soạn lại" },
  { "id": 952, "vietnamese": "Biết ngay mà / Chẳng lạ gì" },
  { "id": 953, "vietnamese": "Rõ rành rành / Biết rồi khổ lắm nói mãi" },
  { "id": 954, "vietnamese": "Đừng ám tôi nữa / Để tôi yên" },
  { "id": 955, "vietnamese": "Tôi hiểu cảm giác đó mà / Tôi từng trải qua rồi" },
  { "id": 956, "vietnamese": "Thiếu người trầm trọng / Làm việc cầm chừng vì thiếu nhân sự" },
  { "id": 957, "vietnamese": "Vấn đề là ở chỗ đó / Khổ nỗi là..." },
  { "id": 958, "vietnamese": "Thú vị phết / Nghe cuốn đấy" },
  { "id": 959, "vietnamese": "Chuyện thường ở huyện / Cơm bữa ấy mà" },
  { "id": 960, "vietnamese": "Không có bằng chứng đâu / Chẳng tóm được đuôi đâu" },
  { "id": 961, "vietnamese": "Cay cú thật chứ / Ức chế vãi" },
  { "id": 962, "vietnamese": "Không biết thì tốt hơn / Biết làm gì cho đau đầu" },
  { "id": 963, "vietnamese": "Hay ho thật / Cuốn hút ghê" },
  { "id": 964, "vietnamese": "Tắc đường sấp mặt / Kẹt xe cứng ngắc" },
  { "id": 965, "vietnamese": "Chuyện đó khác hoàn toàn / Lại là một vấn đề khác rồi" },
  { "id": 966, "vietnamese": "Đáng suy ngẫm / Sâu sắc thật" },
  { "id": 967, "vietnamese": "Hứa danh dự luôn / Lấy danh dự ra đảm bảo" },
  { "id": 968, "vietnamese": "Kể ra thì dài dòng lắm / Chuyện dài lắm" },
  { "id": 969, "vietnamese": "Phải phá cách đi / Đừng đi theo lối mòn nữa" },
  { "id": 970, "vietnamese": "Phải thế chứ! / Chuẩn cơm mẹ nấu rồi!" },
  { "id": 971, "vietnamese": "Ván đã đóng thuyền / Muộn rồi" },
  { "id": 972, "vietnamese": "Ngứa ngáy chân tay quá / Không ngồi yên được" },
  { "id": 973, "vietnamese": "Có còn hơn không / Méo mó có hơn không" },
  { "id": 974, "vietnamese": "Bọn tôi thân nhau từ thời cởi chuồng tắm mưa / Biết nhau từ kiếp nào rồi" },
  { "id": 975, "vietnamese": "Tập trung chuyên môn đi / Đừng lơ là" },
  { "id": 976, "vietnamese": "Lão ý khó chiều lắm / Đòi hỏi cao ngất ngưởng" },
  { "id": 977, "vietnamese": "Bỏ cái rụp luôn / Cai nghiện thành công" },
  { "id": 978, "vietnamese": "Nhớ ngày xưa ghê / Cả bầu trời tuổi thơ ùa về" },
  { "id": 979, "vietnamese": "Cập nhật tình hình đi / Đừng tối cổ thế" },
  { "id": 980, "vietnamese": "Cho con số ước chừng đi / Khoảng bao nhiêu?" },
  { "id": 981, "vietnamese": "Cậu đoán thử xem / Cậu nghĩ khoảng bao nhiêu?" },
  { "id": 982, "vietnamese": "Gai mắt thật / Phiền phức kinh khủng" },
  { "id": 983, "vietnamese": "Luôn phải cảnh giác cao độ / Không được lơ là giây nào" },
  { "id": 984, "vietnamese": "Choáng ngợp luôn / Đỉnh của chóp" },
  { "id": 985, "vietnamese": "Tôi dễ bị dụ lắm / Tôi yếu lòng với cái này lắm" },
  { "id": 986, "vietnamese": "Nói thẳng nhé / Thú thật với cậu" },
  { "id": 987, "vietnamese": "Đáng đời / Gieo gió gặt bão thôi" },
  { "id": 988, "vietnamese": "Nói ngắn gọn thôi nhé / Bỏ qua tiểu tiết nhé" },
  { "id": 989, "vietnamese": "Tiếng dữ đồn xa" },
  { "id": 990, "vietnamese": "Sao mặt dài thượt ra thế? / Sao ủ rũ thế?" },
  { "id": 991, "vietnamese": "Dịp gì thế? / Nay có vụ gì à?" },
  { "id": 992, "vietnamese": "Có chuyện gì vậy? / Sao thế?" },
  { "id": 993, "vietnamese": "Ổng quẩy tưng bừng / Ổng vui nổ trời" },
  { "id": 994, "vietnamese": "Điền vào đơn này / Kê khai vào đây" },
  { "id": 995, "vietnamese": "Chẳng nhớ gì cả / Nghe lạ hoắc" },
  { "id": 996, "vietnamese": "Bị đắp chiếu rồi / Bị hoãn vô thời hạn rồi" },
  { "id": 997, "vietnamese": "Tôi lú luôn rồi / Chẳng hiểu gì sất" },
  { "id": 998, "vietnamese": "Lên 9 tầng mây / Sướng rơn" },
  { "id": 999, "vietnamese": "Vã lắm rồi / Thèm khát sự chú ý" },
  { "id": 1000, "vietnamese": "Dễ ợt ấy mà / Có gì khó đâu" }
]
