[
  { "id": 301, "vietnamese": "Bơ đẹp tôi luôn / Lờ tôi đi như không quen" },
  { "id": 302, "vietnamese": "Ngưu tầm ngưu, mã tầm mã / Mèo khen mèo dài đuôi" },
  { "id": 303, "vietnamese": "Đừng làm mất hứng / Đừng phá đám không khí" },
  { "id": 304, "vietnamese": "Dạo này gầy đi à? / Giảm cân đấy à?" },
  { "id": 305, "vietnamese": "Ngấy quá / Nhiều dầu mỡ quá" },
  { "id": 306, "vietnamese": "Bọn mình thân nhau nhanh thật / Bắt sóng nhanh ghê" },
  { "id": 307, "vietnamese": "Tôi xin nghỉ ốm rồi / Báo bệnh nghỉ làm rồi" },
  { "id": 308, "vietnamese": "Cắt giảm / Bớt bớt lại" },
  { "id": 309, "vietnamese": "Chuồn khỏi / Lén trốn khỏi" },
  { "id": 310, "vietnamese": "Mai mối cho ai / Gán ghép cho ai" },
  { "id": 311, "vietnamese": "Lại nữa rồi / Biết ngay mà" },
  { "id": 312, "vietnamese": "Tôi không muốn ép cậu đâu / Không muốn làm khó cậu" },
  { "id": 313, "vietnamese": "Cậu mà cũng nói được câu đó à / Cậu thì tư cách gì mà nói" },
  { "id": 314, "vietnamese": "Thế mới phải đạo chứ / Thế có phải hay hơn không" },
  { "id": 315, "vietnamese": "Đừng đếm cua trong lỗ / Nói trước bước không qua" },
  { "id": 316, "vietnamese": "Cậu thấy sao? / Vừa ý không?" },
  { "id": 317, "vietnamese": "Mở tiệc / Tổ chức tiệc tùng" },
  { "id": 318, "vietnamese": "Đừng suy diễn quá / Đừng nghĩ ngợi sâu xa quá" },
  { "id": 319, "vietnamese": "Hỏi thử có mất gì đâu / Cứ hỏi đi ngại gì" },
  { "id": 320, "vietnamese": "Cười bể bụng / Buồn cười chết đi được" },
  { "id": 321, "vietnamese": "Chắc tôi xin kiếu / Thôi tôi không làm đâu" },
  { "id": 322, "vietnamese": "Kén cá chọn canh / Khó chiều" },
  { "id": 323, "vietnamese": "Tôi lo cho cậu mà / Tôi quan tâm đến cậu" },
  { "id": 324, "vietnamese": "Đừng hy vọng nhiều quá / Đừng mừng vội" },
  { "id": 325, "vietnamese": "Khó bảo / Nghịch như quỷ" },
  { "id": 326, "vietnamese": "Nói sao nhỉ... / Diễn tả thế nào đây..." },
  { "id": 327, "vietnamese": "Cho cún ngủ giấc ngàn thu / An tử cho chó" },
  { "id": 328, "vietnamese": "Thượng đội hạ đạp / Nịnh trên nạt dưới" },
  { "id": 329, "vietnamese": "Của nợ / Thứ vô dụng tốn kém" },
  { "id": 330, "vietnamese": "Ngoài giòn trong mềm / Vỏ giòn tan, ruột mềm mại" },
  { "id": 331, "vietnamese": "Anh ta từ đâu chui ra vậy / Tự nhiên lù lù xuất hiện" },
  { "id": 332, "vietnamese": "Màu đỏ tươi / Đỏ thẫm" },
  { "id": 333, "vietnamese": "Kể tôi nghe với / Cập nhật tình hình cho tôi đi" },
  { "id": 334, "vietnamese": "Tôi bị trấn lột / Bị cướp giữa đường" },
  { "id": 335, "vietnamese": "Đừng hiểu lầm, nghe tôi nói đã / Không phải ý đó đâu, nghe này" },
  { "id": 336, "vietnamese": "Huyền thoại / Mang tính biểu tượng" },
  { "id": 337, "vietnamese": "Gió lùa lạnh quá / Hở gió" },
  { "id": 338, "vietnamese": "Thợ mát-xa / Nhân viên massage" },
  { "id": 339, "vietnamese": "Ức chế thật / Bực mình ghê" },
  { "id": 340, "vietnamese": "Kín đáo / Không ồn ào" },
  { "id": 341, "vietnamese": "Đừng chơi trội / Đừng làm mình nổi bật" },
  { "id": 342, "vietnamese": "Nơi trú ẩn an toàn / Bến đỗ bình yên" },
  { "id": 343, "vietnamese": "Đừng có lố quá / Bớt diễn đi" },
  { "id": 344, "vietnamese": "Cạn kiệt năng lượng rồi / Mệt rã rời" },
  { "id": 345, "vietnamese": "Đáng đời / Cho chừa" },
  { "id": 346, "vietnamese": "Chơi luôn / Duyệt" },
  { "id": 347, "vietnamese": "Chán thế / Tiếc nhỉ" },
  { "id": 348, "vietnamese": "Cô ta hay bép xép lắm / Cái loa phát thanh đấy" },
  { "id": 349, "vietnamese": "Vụng về / Tay chân lóng ngóng" },
  { "id": 350, "vietnamese": "Chuyện này dẫn qua chuyện kia / Cứ thế mà thành ra vậy" },
  { "id": 351, "vietnamese": "Trời đất ơi cậu đang làm cái gì thế? / Cậu bị làm sao đấy?" },
  { "id": 352, "vietnamese": "Tắm nắng / Hưởng thụ ánh nắng" },
  { "id": 353, "vietnamese": "Tôi bắt quả tang tại trận / Bắt tận tay day tận mặt" },
  { "id": 354, "vietnamese": "Trời nóng thế này sao cưỡng lại bia tươi được / Nóng vầy làm ly bia tươi là hết bài" },
  { "id": 355, "vietnamese": "Còn cậu thì sao? / Cậu thế nào?" },
  { "id": 356, "vietnamese": "Đúng cái tôi cần đây rồi / Chuẩn bài rồi" },
  { "id": 357, "vietnamese": "Những cột mốc cuộc đời / Giai đoạn chuyển giao trong đời" },
  { "id": 358, "vietnamese": "Nịnh bợ / Bợ đít" },
  { "id": 359, "vietnamese": "Chuẩn mẫu chồng lý tưởng / Chồng quốc dân tương lai" },
  { "id": 360, "vietnamese": "Tôi cứ nhầm lẫn lung tung / Tôi hay bị lộn" },
  { "id": 361, "vietnamese": "Dần dần thấy thích / Càng nhìn càng ưng" },
  { "id": 362, "vietnamese": "Ai mà ngờ được chứ / Ai mà tin nổi" },
  { "id": 363, "vietnamese": "Kẻ láu cá / Tên lừa đảo tinh vi" },
  { "id": 364, "vietnamese": "Cuốn hút / Hớp hồn" },
  { "id": 365, "vietnamese": "Bạn thân chí cốt / Chị em cây khế" },
  { "id": 366, "vietnamese": "Đâm sau lưng / Phản bội" },
  { "id": 367, "vietnamese": "Thử sức xem sao / Thử làm cái coi" },
  { "id": 368, "vietnamese": "Đó là nghề của tôi, không phải của cậu / Sở trường của tôi mà" },
  { "id": 369, "vietnamese": "Lặn mất tăm / Biến mất không dấu vết" },
  { "id": 370, "vietnamese": "Chắc chắn 100% / Không còn nghi ngờ gì nữa" },
  { "id": 371, "vietnamese": "Hình như là / Nghe đồn là" },
  { "id": 372, "vietnamese": "Tự lực cánh sinh / Một mình tôi lo" },
  { "id": 373, "vietnamese": "Thảm họa / Mớ hỗn độn nát bét" },
  { "id": 374, "vietnamese": "Người đi kèm / Bảo mẫu (nghĩa bóng)" },
  { "id": 375, "vietnamese": "Thoát khỏi / Phá vỡ xiềng xích" },
  { "id": 376, "vietnamese": "Nghe như học thuộc lòng ấy / Nghe giả trân" },
  { "id": 377, "vietnamese": "Tiền đền bù thôi việc / Trợ cấp mất việc" },
  { "id": 378, "vietnamese": "Khóc lóc cái gì / Ai quan tâm chứ" },
  { "id": 379, "vietnamese": "Đừng giả ngu / Đừng giả nai" },
  { "id": 380, "vietnamese": "Kín tiếng / Không phô trương" },
  { "id": 381, "vietnamese": "Mì trương phình rồi / Mì nở hết rồi" },
  { "id": 382, "vietnamese": "Tôi giật giải cuộc thi vẽ đấy / Tôi thắng giải mỹ thuật" },
  { "id": 383, "vietnamese": "Cục vàng của tôi / Người thương nhất đời" },
  { "id": 384, "vietnamese": "Chân tôi bị tê / Tê chân quá" },
  { "id": 385, "vietnamese": "Tôi có chọn đâu / Không phải tôi chọn" },
  { "id": 386, "vietnamese": "Việc ngập đầu rồi / Bận tối mắt tối mũi" },
  { "id": 387, "vietnamese": "Cứ bắt đầu từ đó đi / Tính từ đó nhé" },
  { "id": 388, "vietnamese": "Khóa quần chưa kéo kìa / Cửa sổ mở toang hoác kìa" },
  { "id": 389, "vietnamese": "Pizza luôn thấu hiểu / Chỉ có pizza là không phán xét" },
  { "id": 390, "vietnamese": "Thôi tôi lượn đây / Tôi phải đi rồi" },
  { "id": 391, "vietnamese": "Sao bỏ đi khơi khơi vậy được / Cậu không thể cứ thế mà đi" },
  { "id": 392, "vietnamese": "Nghĩ cho kỹ vào / Tính toán cho cẩn thận" },
  { "id": 393, "vietnamese": "Có nằm mơ tôi cũng không biết / Ai mà dè" },
  { "id": 394, "vietnamese": "Cảnh sau credit / Đoạn phim tặng kèm cuối phim" },
  { "id": 395, "vietnamese": "Vẫn nguyên vẹn / Không sứt mẻ gì" },
  { "id": 396, "vietnamese": "Lạc quẻ quá / Tự nhiên ất ơ đâu ra" },
  { "id": 397, "vietnamese": "Vợ chồng son / Cặp đôi mới cưới" },
  { "id": 398, "vietnamese": "Cánh tả / Phe tư tưởng cấp tiến" },
  { "id": 399, "vietnamese": "Nói một cách chính xác thì / Về mặt kỹ thuật mà nói" },
  { "id": 400, "vietnamese": "Không muốn nhận đâu nhưng mà... / Ghét phải thừa nhận là..." }
]
